leximpact_aggregates/__init__.py
leximpact_aggregates/_modidx.py
leximpact_aggregates/_nbdev.py
leximpact_aggregates/aggregate.py
leximpact_aggregates-0.0.50.dist-info/METADATA
leximpact_aggregates-0.0.50.dist-info/WHEEL
leximpact_aggregates-0.0.50.dist-info/licenses/LICENSE
leximpact_aggregates-0.0.50.dist-info/licenses/LICENSE.md
leximpact_aggregates-0.0.50.dist-info/RECORD
