Metadata-Version: 2.4
Name: leximpact_aggregates
Version: 0.0.50
Summary: Store aggregates of french data.
License: AGPL-3.0
License-File: LICENSE
License-File: LICENSE.md
Author: LexImpact
Requires-Python: >=3.10,<4.0
Classifier: License :: OSI Approved :: GNU Affero General Public License v3
Classifier: Programming Language :: Python :: 3
Classifier: Programming Language :: Python :: 3.10
Classifier: Programming Language :: Python :: 3.11
Classifier: Programming Language :: Python :: 3.12
Classifier: Programming Language :: Python :: 3.13
Classifier: Programming Language :: Python :: 3.14
Requires-Dist: StrEnum (>=0.4.15,<0.5.0)
Requires-Dist: dataclasses-json (>=0.6.7,<0.7.0)
Requires-Dist: ipykernel (>=6.29.5,<7.0.0)
Requires-Dist: numpy
Requires-Dist: pandas (>=2.3.0,<3.0.0)
Requires-Dist: requests (>=2.32.3,<3.0.0)
Requires-Dist: ruamel-yaml (>=0.18.14,<0.19.0)
Requires-Dist: tqdm (>=4.67.1,<5.0.0)
